tlint/__init__.py
tlint/__main__.py
tlint/configuration.py
tlint/loader.py
tlint/tlint.py
tlint-0.0.2.dist-info/METADATA
tlint-0.0.2.dist-info/WHEEL
tlint-0.0.2.dist-info/entry_points.txt
tlint-0.0.2.dist-info/top_level.txt
tlint-0.0.2.dist-info/RECORD
