Metadata-Version: 2.1
Name: tlint
Version: 0.0.2
Summary: Linter which behaviour is entirely based on a config file.
Home-page: UNKNOWN
License: UNKNOWN
Platform: UNKNOWN
